crewcal/__init__.py
crewcal/cli.py
crewcal/hotel.py
crewcal/llm_extract.py
crewcal/llm_prompts.py
crewcal/schedule.py
crewcal/temp.txt
crewcal/wip.py
crewcal-0.9.0.dist-info/LICENSE.txt
crewcal-0.9.0.dist-info/METADATA
crewcal-0.9.0.dist-info/WHEEL
crewcal-0.9.0.dist-info/entry_points.txt
crewcal-0.9.0.dist-info/RECORD
