Metadata-Version: 2.1
Name: crewcal
Version: 0.9.0
Summary: Convert an airline crew schedule pdf into iCalendar format.
Home-page: https://github.com/EJOOSTEROP/crewcal
License: MIT
Keywords: x,y,z
Author: Erik Oosterop
Author-email: ni7h4txi@duck.com
Requires-Python: >=3.11,<4.0
Classifier: License :: OSI Approved :: MIT License
Classifier: Programming Language :: Python :: 3
Classifier: Programming Language :: Python :: 3.11
Classifier: Programming Language :: Python :: 3.12
Requires-Dist: click (>=8.1.7,<9.0.0)
Requires-Dist: halo (>=0.0.31,<0.0.32)
Requires-Dist: ics (>=0.7.2,<0.8.0)
Requires-Dist: langchain (>=0.0.337,<0.0.338)
Requires-Dist: openai (>=1.3.3,<2.0.0)
Requires-Dist: pendulum (>=2.1.2,<3.0.0)
Requires-Dist: pydantic (>=2.5.1,<3.0.0)
Requires-Dist: pypdf (>=3.17.1,<4.0.0)
Requires-Dist: python-dotenv (>=1.0.0,<2.0.0)
Project-URL: Documentation, https://github.com/EJOOSTEROP/crewcal
Project-URL: Repository, https://github.com/EJOOSTEROP/crewcal
